py_velocity_topology_parser/VelocityTopologyParser.py
py_velocity_topology_parser/__init__.py
py_velocity_topology_parser-0.1.dist-info/LICENSE
py_velocity_topology_parser-0.1.dist-info/METADATA
py_velocity_topology_parser-0.1.dist-info/WHEEL
py_velocity_topology_parser-0.1.dist-info/top_level.txt
py_velocity_topology_parser-0.1.dist-info/zip-safe
py_velocity_topology_parser-0.1.dist-info/RECORD
